{"Id":{"Type":1,"Identifier":"multi-asset"},"Transforms":[{"Position":{"x":-0.6520000100135803,"y":0.3659999966621399,"z":0.0},"Rotation":{"x":0.30919116735458376,"y":-0.31486621499061587,"z":0.10930272191762924,"w":0.8906812071800232},"Scale":{"x":1.0,"y":0.5463100075721741,"z":0.8340100049972534}},{"Position":{"x":1.465000033378601,"y":0.0,"z":0.0},"Rotation":{"x":0.0,"y":0.0,"z":0.0,"w":1.0},"Scale":{"x":1.0,"y":1.0,"z":1.0}},{"Position":{"x":0.6800000071525574,"y":0.0,"z":8.0600004196167},"Rotation":{"x":0.0,"y":0.0,"z":0.0,"w":1.0},"Scale":{"x":3.0,"y":3.0,"z":3.0}}],"Children":[{"Type":0,"Identifier":"evil-cylinder1"},{"Type":0,"Identifier":"evil-cylinder2"},{"Type":0,"Identifier":"the-god-cube"}],"Metadata":{"Paths":["multi-asset","multi-asset/evil-cylinder1","multi-asset/evil-cylinder2","multi-asset/the-god-cube","multi-asset/evil-cylinder1/delta","multi-asset/evil-cylinder2/delta","multi-asset/the-god-cube/delta-evil","multi-asset/the-god-cube/delta-sphere","multi-asset/evil-cylinder1/delta/wobble-sphere","multi-asset/evil-cylinder2/delta/wobble-sphere","multi-asset/the-god-cube/delta-evil/evil-cylinder","multi-asset/the-god-cube/delta-sphere/wobble-sphere","multi-asset/evil-cylinder1/delta/wobble-sphere/wobble-sphere","multi-asset/evil-cylinder2/delta/wobble-sphere/wobble-sphere","multi-asset/the-god-cube/delta-evil/evil-cylinder/evil-cylinder","multi-asset/the-god-cube/delta-sphere/wobble-sphere/wobble-sphere","multi-asset/evil-cylinder1/delta/wobble-sphere/wobble-sphere/animations","multi-asset/evil-cylinder2/delta/wobble-sphere/wobble-sphere/animations","multi-asset/the-god-cube/delta-evil/evil-cylinder/evil-cylinder/delta","multi-asset/the-god-cube/delta-sphere/wobble-sphere/wobble-sphere/animations","multi-asset/the-god-cube/delta-evil/evil-cylinder/evil-cylinder/delta/wobble-sphere","multi-asset/the-god-cube/delta-evil/evil-cylinder/evil-cylinder/delta/wobble-sphere/wobble-sphere","multi-asset/the-god-cube/delta-evil/evil-cylinder/evil-cylinder/delta/wobble-sphere/wobble-sphere/animations"],"Data":["0@identifier:multi-asset","1@identifier:evil-cylinder1","1@key:evil-cylinder","2@identifier:evil-cylinder2","2@key:evil-cylinder","3@identifier:the-god-cube","3@key:gracious-cube","4@identifier:delta","4@input:vec3:position","4@input:vec3:rotation","4@input:vec3:scale","4@input:vec3:position_delta","4@input:vec3:rotation_delta","4@input:vec3:scale_delta","4@input:bool:isLocal","5@identifier:delta","5@input:vec3:position","5@input:vec3:rotation","5@input:vec3:scale","5@input:vec3:position_delta","5@input:vec3:rotation_delta","5@input:vec3:scale_delta","5@input:bool:isLocal","6@identifier:delta-evil","6@input:vec3:position","6@input:vec3:rotation","6@input:vec3:scale","6@input:vec3:position_delta","6@input:vec3:rotation_delta","6@input:vec3:scale_delta","6@input:bool:isLocal","7@identifier:delta-sphere","7@input:vec3:position","7@input:vec3:rotation","7@input:vec3:scale","7@input:vec3:position_delta","7@input:vec3:rotation_delta","7@input:vec3:scale_delta","7@input:bool:isLocal","8@identifier:wobble-sphere","9@identifier:wobble-sphere","10@identifier:evil-cylinder","11@identifier:wobble-sphere","12@identifier:wobble-sphere","12@key:wobble-sphere","13@identifier:wobble-sphere","13@key:wobble-sphere","14@identifier:evil-cylinder","14@key:evil-cylinder","15@identifier:wobble-sphere","15@key:wobble-sphere","16@identifier:animations","16@input:void:Still","16@input:void:Wobble","16@input:void:Bounce","17@identifier:animations","17@input:void:Still","17@input:void:Wobble","17@input:void:Bounce","18@identifier:delta","18@input:vec3:position","18@input:vec3:rotation","18@input:vec3:scale","18@input:vec3:position_delta","18@input:vec3:rotation_delta","18@input:vec3:scale_delta","18@input:bool:isLocal","19@identifier:animations","19@input:void:Still","19@input:void:Wobble","19@input:void:Bounce","20@identifier:wobble-sphere","21@identifier:wobble-sphere","21@key:wobble-sphere","22@identifier:animations","22@input:void:Still","22@input:void:Wobble","22@input:void:Bounce"]}}